authentication_middleware/__init__.py
authentication_middleware/middleware.py
authentication_middleware-0.1.0.dist-info/METADATA
authentication_middleware-0.1.0.dist-info/WHEEL
authentication_middleware-0.1.0.dist-info/RECORD
